{"stats":{"minecraft:crafted":{"minecraft:ender_chest":16,"minecraft:black_dye":8,"minecraft:smooth_stone":137,"minecraft:oak_sign":6,"minecraft:dark_oak_pressure_plate":14,"minecraft:chain":107,"minecraft:blaze_powder":16,"minecraft:dark_oak_wood":9,"minecraft:loom":2,"minecraft:lever":62,"minecraft:diamond_shovel":1,"minecraft:bookshelf":84,"minecraft:cooked_mutton":71,"minecraft:iron_bars":16,"minecraft:glass":50,"minecraft:repeater":40,"minecraft:diamond_helmet":1,"minecraft:diamond_leggings":1,"minecraft:stone_pressure_plate":1,"minecraft:iron_door":6,"minecraft:magenta_dye":1,"minecraft:flower_pot":8,"minecraft:wooden_shovel":2,"minecraft:emerald":2273,"minecraft:cooked_porkchop":13,"minecraft:diamond_axe":1,"minecraft:polished_andesite_stairs":64,"minecraft:chest_minecart":4,"minecraft:spruce_door":42,"minecraft:smithing_table":3,"minecraft:copper_ingot":59,"minecraft:sticky_piston":3,"minecraft:fletching_table":8,"minecraft:hay_block":20,"minecraft:campfire":25,"minecraft:painting":9,"minecraft:lectern":19,"minecraft:golden_leggings":2,"minecraft:stone_slab":48,"minecraft:compass":9,"minecraft:iron_pickaxe":26,"minecraft:iron_block":96,"minecraft:gold_ingot":481,"minecraft:netherite_ingot":13,"minecraft:composter":5,"minecraft:spruce_fence_gate":13,"minecraft:golden_carrot":213,"minecraft:smooth_stone_slab":42,"minecraft:leather_leggings":2,"minecraft:iron_nugget":2130,"minecraft:spyglass":3,"minecraft:bone_meal":774,"minecraft:spruce_fence":687,"minecraft:pink_dye":1,"minecraft:white_carpet":24,"minecraft:stone_stairs":88,"minecraft:lantern":291,"minecraft:dark_oak_fence":90,"minecraft:spruce_stairs":432,"minecraft:detector_rail":6,"minecraft:polished_diorite":64,"minecraft:ladder":114,"minecraft:spruce_slab":1374,"minecraft:stone_pickaxe":2,"minecraft:diamond_boots":1,"minecraft:spruce_boat":5,"minecraft:redstone_block":307,"minecraft:dark_oak_planks":4573,"minecraft:golden_helmet":1,"minecraft:wheat":576,"minecraft:coal_block":236,"minecraft:netherite_pickaxe":1,"minecraft:enchanting_table":1,"minecraft:polished_granite":104,"minecraft:leather_helmet":2,"minecraft:dark_oak_button":4,"minecraft:red_carpet":225,"minecraft:enchanted_book":52,"minecraft:oak_fence_gate":2,"minecraft:warped_fungus_on_a_stick":2,"minecraft:wooden_axe":1,"minecraft:iron_shovel":14,"minecraft:iron_leggings":6,"minecraft:armor_stand":8,"minecraft:white_bed":23,"minecraft:brick":32,"minecraft:grindstone":3,"minecraft:oak_planks":776,"minecraft:cobblestone_slab":72,"minecraft:barrel":42,"minecraft:cooked_chicken":48,"minecraft:cobblestone_stairs":44,"minecraft:stone":909,"minecraft:snow":354,"minecraft:heavy_weighted_pressure_plate":3,"minecraft:spruce_pressure_plate":24,"minecraft:suspicious_stew":14,"minecraft:dark_oak_door":18,"minecraft:hopper":48,"minecraft:bow":10,"minecraft:iron_boots":6,"minecraft:comparator":8,"minecraft:chest":185,"minecraft:copper_block":6,"minecraft:rail":128,"minecraft:ender_eye":16,"minecraft:stone_bricks":384,"minecraft:oak_fence":24,"minecraft:golden_sword":2,"minecraft:golden_boots":3,"minecraft:white_banner":2,"minecraft:oak_slab":18,"minecraft:item_frame":17,"minecraft:arrow":320,"minecraft:cauldron":3,"minecraft:map":8,"minecraft:crafting_table":116,"minecraft:spruce_planks":37762,"minecraft:wooden_pickaxe":1,"minecraft:iron_helmet":6,"minecraft:red_wool":151,"minecraft:gold_block":31,"minecraft:birch_planks":80,"minecraft:dispenser":1,"minecraft:apple":28,"minecraft:spruce_trapdoor":106,"minecraft:dark_oak_slab":426,"minecraft:iron_chestplate":6,"minecraft:book":225,"minecraft:paper":1377,"minecraft:diamond_pickaxe":2,"minecraft:emerald_block":64,"minecraft:shield":6,"minecraft:stick":59392,"minecraft:light_weighted_pressure_plate":6,"minecraft:leather_chestplate":2,"minecraft:iron_ingot":1099,"minecraft:andesite_stairs":40,"minecraft:stone_sword":1,"minecraft:snow_block":288,"minecraft:black_bed":193,"minecraft:redstone_torch":130,"minecraft:shears":9,"minecraft:polished_andesite":332,"minecraft:oak_door":6,"minecraft:cookie":288,"minecraft:redstone":369,"minecraft:coal":1206,"minecraft:tripwire_hook":2,"minecraft:fishing_rod":2,"minecraft:stone_brick_wall":174,"minecraft:leather_boots":2,"minecraft:golden_chestplate":1,"minecraft:spruce_button":34,"minecraft:furnace":27,"minecraft:stone_button":19,"minecraft:piston":5,"minecraft:dark_oak_trapdoor":256,"minecraft:glass_pane":384,"minecraft:diamond_block":20,"minecraft:oak_trapdoor":14,"minecraft:flint_and_steel":1,"minecraft:netherite_chestplate":1,"minecraft:netherite_leggings":1,"minecraft:iron_axe":7,"minecraft:spruce_wood":60,"minecraft:iron_hoe":5,"minecraft:slime_ball":5,"minecraft:filled_map":17,"minecraft:netherite_scrap":52,"minecraft:minecart":4,"minecraft:cooked_beef":168,"minecraft:red_dye":157,"minecraft:diamond_sword":1,"minecraft:spruce_sign":9,"minecraft:dark_oak_stairs":516,"minecraft:powered_rail":240,"minecraft:iron_sword":6,"minecraft:black_banner":1,"minecraft:nether_bricks":13,"minecraft:cooked_salmon":6,"minecraft:bucket":8,"minecraft:stone_axe":1,"minecraft:lodestone":1,"minecraft:air":0,"minecraft:bread":254,"minecraft:blue_dye":6,"minecraft:white_wool":27,"minecraft:white_dye":8,"minecraft:netherite_shovel":1,"minecraft:blue_wool":1,"minecraft:anvil":6,"minecraft:stonecutter":1,"minecraft:pumpkin_pie":48,"minecraft:torch":1256,"minecraft:lapis_lazuli":99,"minecraft:lapis_block":96,"minecraft:trapped_chest":2,"minecraft:diamond_chestplate":2},"minecraft:killed":{"minecraft:cave_spider":3,"minecraft:skeleton":250,"minecraft:fox":2,"minecraft:chicken":29,"minecraft:magma_cube":127,"minecraft:salmon":6,"minecraft:iron_golem":1,"minecraft:pillager":43,"minecraft:zombie":1591,"minecraft:cow":330,"minecraft:evoker":1,"minecraft:endermite":1,"minecraft:vindicator":10,"minecraft:rabbit":2,"minecraft:wandering_trader":2,"minecraft:ravager":4,"minecraft:polar_bear":1,"minecraft:enderman":30,"minecraft:witch":8,"minecraft:spider":157,"minecraft:piglin_brute":14,"minecraft:piglin":29,"minecraft:pig":24,"minecraft:zombie_villager":9,"minecraft:creeper":153,"minecraft:sheep":41,"minecraft:trader_llama":4,"minecraft:stray":47,"minecraft:blaze":43,"minecraft:vex":4,"minecraft:phantom":10,"minecraft:drowned":1,"minecraft:bat":1,"minecraft:hoglin":17,"minecraft:squid":8,"minecraft:wither_skeleton":44},"minecraft:mined":{"minecraft:dark_oak_planks":652,"minecraft:white_bed":2,"minecraft:obsidian":366,"minecraft:carved_pumpkin":11,"minecraft:granite":1430,"minecraft:stone_brick_wall":6,"minecraft:hopper":60,"minecraft:oxeye_daisy":41,"minecraft:polished_blackstone_bricks":285,"minecraft:weeping_vines_plant":1,"minecraft:magma_block":944,"minecraft:dark_oak_trapdoor":56,"minecraft:fire":547,"minecraft:barrel":29,"minecraft:pumpkin":36,"minecraft:fletching_table":9,"minecraft:enchanting_table":1,"minecraft:dirt_path":10,"minecraft:oak_stairs":1,"minecraft:spruce_pressure_plate":2,"minecraft:pink_tulip":49,"minecraft:spruce_wood":10,"minecraft:white_banner":1,"minecraft:piston_head":2,"minecraft:red_bed":2,"minecraft:kelp_plant":1,"minecraft:crimson_nylium":58,"minecraft:amethyst_cluster":5,"minecraft:powder_snow":2,"minecraft:torch":194,"minecraft:dark_oak_wood":7,"minecraft:white_stained_glass_pane":1,"minecraft:spruce_wall_sign":1,"minecraft:glass":1,"minecraft:sugar_cane":1112,"minecraft:bricks":1,"minecraft:spruce_sign":4,"minecraft:amethyst_block":16,"minecraft:chain":38,"minecraft:repeater":22,"minecraft:wheat":1666,"minecraft:lilac":10,"minecraft:pumpkin_stem":10,"minecraft:black_bed":8,"minecraft:warped_fungus":2,"minecraft:grass":3360,"minecraft:dark_oak_sapling":2,"minecraft:loom":1,"minecraft:mossy_cobblestone":82,"minecraft:dark_oak_log":1391,"minecraft:nether_bricks":9,"minecraft:dark_oak_fence":23,"minecraft:allium":41,"minecraft:spruce_fence":501,"minecraft:crimson_roots":6,"minecraft:redstone_wire":146,"minecraft:redstone_ore":944,"minecraft:snow":1204,"minecraft:andesite":1725,"minecraft:diamond_block":15,"minecraft:potatoes":195,"minecraft:rail":42,"minecraft:cobblestone_slab":67,"minecraft:warped_stem":18,"minecraft:bamboo_sapling":3,"minecraft:bamboo":243,"minecraft:white_wool":1,"minecraft:ender_chest":17,"minecraft:oak_slab":1,"minecraft:redstone_block":5,"minecraft:glass_pane":15,"minecraft:comparator":9,"minecraft:soul_sand":81,"minecraft:lily_of_the_valley":24,"minecraft:dandelion":8,"minecraft:cornflower":36,"minecraft:warped_roots":6,"minecraft:campfire":22,"minecraft:copper_ore":160,"minecraft:tall_grass":249,"minecraft:diorite":1341,"minecraft:warped_wart_block":25,"minecraft:purple_bed":5,"minecraft:cobblestone_wall":1,"minecraft:white_carpet":4,"minecraft:spruce_log":12796,"minecraft:birch_leaves":13,"minecraft:dark_oak_button":12,"minecraft:gravel":1740,"minecraft:cobweb":60,"minecraft:spruce_fence_gate":7,"minecraft:stone_bricks":7,"minecraft:gold_ore":210,"minecraft:chipped_anvil":2,"minecraft:fern":45,"minecraft:spruce_planks":1304,"minecraft:farmland":38,"minecraft:cobblestone_stairs":22,"minecraft:spruce_trapdoor":55,"minecraft:grass_block":5049,"minecraft:cracked_polished_blackstone_bricks":205,"minecraft:polished_diorite":2,"minecraft:composter":12,"minecraft:smooth_stone":9,"minecraft:glowstone":103,"minecraft:iron_ore":1342,"minecraft:anvil":1,"minecraft:azure_bluet":41,"minecraft:dark_oak_stairs":169,"minecraft:red_tulip":31,"minecraft:iron_bars":8,"minecraft:spruce_slab":1335,"minecraft:blackstone":322,"minecraft:twisting_vines_plant":1,"minecraft:clay":13,"minecraft:calcite":4,"minecraft:poppy":170,"minecraft:chest":49,"minecraft:nether_quartz_ore":2488,"minecraft:cobblestone":1409,"minecraft:grindstone":6,"minecraft:oak_planks":22,"minecraft:iron_door":12,"minecraft:wall_torch":359,"minecraft:cauldron":2,"minecraft:stone_stairs":57,"minecraft:light_weighted_pressure_plate":1,"minecraft:warped_nylium":129,"minecraft:blue_terracotta":1,"minecraft:powered_rail":27,"minecraft:dark_oak_slab":85,"minecraft:dark_oak_door":12,"minecraft:nether_wart_block":1,"minecraft:birch_log":20,"minecraft:orange_tulip":15,"minecraft:smooth_stone_slab":2,"minecraft:oak_log":192,"minecraft:sand":112,"minecraft:dirt":4258,"minecraft:dispenser":1,"minecraft:netherrack":15432,"minecraft:ancient_debris":50,"minecraft:oak_leaves":76,"minecraft:nether_gold_ore":166,"minecraft:diamond_ore":155,"minecraft:red_carpet":34,"minecraft:tuff":3,"minecraft:dark_oak_leaves":39,"minecraft:lever":23,"minecraft:ladder":6,"minecraft:stone_button":11,"minecraft:weeping_vines":1,"minecraft:spruce_leaves":1835,"minecraft:large_fern":75,"minecraft:hay_block":76,"minecraft:oak_trapdoor":6,"minecraft:spruce_sapling":240,"minecraft:furnace":2,"minecraft:carrots":128,"minecraft:nether_sprouts":1,"minecraft:stripped_spruce_log":17,"minecraft:detector_rail":3,"minecraft:peony":9,"minecraft:gold_block":21,"minecraft:nether_brick_fence":3,"minecraft:bookshelf":50,"minecraft:lantern":62,"minecraft:stripped_oak_log":1,"minecraft:white_tulip":63,"minecraft:stone":24636,"minecraft:redstone_wall_torch":9,"minecraft:podzol":85,"minecraft:stripped_dark_oak_log":1,"minecraft:basalt":15,"minecraft:spruce_door":22,"minecraft:polished_granite":10,"minecraft:oak_fence":12,"minecraft:crafting_table":25,"minecraft:rose_bush":3,"minecraft:lectern":845,"minecraft:stone_slab":33,"minecraft:lapis_ore":90,"minecraft:polished_blackstone_brick_stairs":7,"minecraft:blue_bed":5,"minecraft:spruce_stairs":171,"minecraft:redstone_torch":12,"minecraft:ice":78,"minecraft:white_wall_banner":1,"minecraft:bee_nest":1,"minecraft:coal_ore":2530,"minecraft:cocoa":7,"minecraft:flower_pot":1,"minecraft:lodestone":1,"minecraft:polished_andesite":19},"minecraft:picked_up":{"minecraft:iron_chestplate":3,"minecraft:chainmail_boots":2,"minecraft:flower_pot":1,"minecraft:anvil":1,"minecraft:suspicious_stew":1,"minecraft:lead":8,"minecraft:stone_slab":43,"minecraft:enchanted_book":6,"minecraft:golden_sword":2,"minecraft:amethyst_block":32,"minecraft:polished_blackstone_brick_stairs":3,"minecraft:string":384,"minecraft:dark_oak_trapdoor":56,"minecraft:cooked_salmon":10,"minecraft:diamond_leggings":1,"minecraft:gold_nugget":931,"minecraft:spruce_planks":1615,"minecraft:dark_oak_door":15,"minecraft:golden_helmet":8,"minecraft:spruce_pressure_plate":2,"minecraft:composter":14,"minecraft:golden_chestplate":5,"minecraft:cauldron":3,"minecraft:stone_sword":6,"minecraft:command_block":1,"minecraft:red_tulip":34,"minecraft:carved_pumpkin":11,"minecraft:glowstone":100,"minecraft:bookshelf":43,"minecraft:netherite_chestplate":5,"minecraft:blaze_rod":26,"minecraft:iron_bars":8,"minecraft:snowball":1453,"minecraft:birch_log":43,"minecraft:magma_block":366,"minecraft:feather":31,"minecraft:cooked_beef":724,"minecraft:iron_door":12,"minecraft:water_bucket":11,"minecraft:flint":1854,"minecraft:netherite_leggings":4,"minecraft:lantern":197,"minecraft:chipped_anvil":2,"minecraft:stonecutter":1,"minecraft:glowstone_dust":5,"minecraft:warped_wart_block":13,"minecraft:stripped_spruce_log":17,"minecraft:ink_sac":31,"minecraft:loom":1,"minecraft:dark_oak_log":1479,"minecraft:barrel":34,"minecraft:iron_hoe":3,"minecraft:polished_andesite":76,"minecraft:dispenser":1,"minecraft:blue_terracotta":1,"minecraft:lever":39,"minecraft:granite":1524,"minecraft:chainmail_helmet":1,"minecraft:bread":145,"minecraft:dark_oak_fence":23,"minecraft:bricks":1,"minecraft:spruce_leaves":405,"minecraft:crafting_table":26,"minecraft:bee_nest":1,"minecraft:clay_ball":96,"minecraft:leather_leggings":8,"minecraft:cornflower":23,"minecraft:red_bed":2,"minecraft:compass":2,"minecraft:white_carpet":2,"minecraft:iron_shovel":5,"minecraft:glass_pane":13,"minecraft:netherite_sword":7,"minecraft:beef":367,"minecraft:iron_nugget":76,"minecraft:poppy":160,"minecraft:spruce_slab":1507,"minecraft:minecart":22,"minecraft:chest":47,"minecraft:birch_sapling":3,"minecraft:egg":34,"minecraft:copper_ore":167,"minecraft:stone":7597,"minecraft:spruce_fence":727,"minecraft:carrot":375,"minecraft:redstone":4215,"minecraft:netherite_pickaxe":11,"minecraft:prismarine_crystals":6,"minecraft:tnt":3,"minecraft:diamond_chestplate":1,"minecraft:cooked_cod":5,"minecraft:beetroot_seeds":1,"minecraft:peony":8,"minecraft:shears":5,"minecraft:hay_block":80,"minecraft:gold_ingot":2,"minecraft:totem_of_undying":4,"minecraft:mutton":74,"minecraft:white_wool":268,"minecraft:rail":67,"minecraft:oxeye_daisy":37,"minecraft:stripped_oak_log":1,"minecraft:red_mushroom":1,"minecraft:filled_map":11,"minecraft:oak_log":244,"minecraft:ancient_debris":52,"minecraft:golden_boots":13,"minecraft:blue_bed":6,"minecraft:white_banner":17,"minecraft:apple":20,"minecraft:stone_bricks":57,"minecraft:warped_stem":17,"minecraft:stone_pickaxe":1,"minecraft:iron_ore":1345,"minecraft:iron_sword":12,"minecraft:dark_oak_stairs":168,"minecraft:dark_oak_slab":127,"minecraft:white_stained_glass_pane":1,"minecraft:spyglass":2,"minecraft:gravel":310,"minecraft:spruce_sapling":1640,"minecraft:spruce_log":13565,"minecraft:leather_helmet":4,"minecraft:coal_ore":21,"minecraft:purple_bed":5,"minecraft:polished_diorite":66,"minecraft:stone_axe":7,"minecraft:redstone_ore":17,"minecraft:painting":77,"minecraft:gray_wool":3,"minecraft:warped_roots":16,"minecraft:lodestone":1,"minecraft:warped_nylium":3,"minecraft:stripped_dark_oak_log":1,"minecraft:crimson_nylium":2,"minecraft:hopper":53,"minecraft:ender_pearl":52,"minecraft:wheat":1678,"minecraft:redstone_block":46,"minecraft:ender_chest":22,"minecraft:potion":1,"minecraft:smooth_stone_slab":3,"minecraft:iron_leggings":6,"minecraft:armor_stand":3,"minecraft:sticky_piston":2,"minecraft:smooth_stone":9,"minecraft:comparator":10,"minecraft:dark_oak_leaves":11,"minecraft:light_weighted_pressure_plate":3,"minecraft:white_tulip":98,"minecraft:rose_bush":2,"minecraft:redstone_torch":36,"minecraft:cobblestone_slab":65,"minecraft:calcite":16,"minecraft:iron_pickaxe":7,"minecraft:iron_boots":4,"minecraft:furnace":3,"minecraft:tipped_arrow":39,"minecraft:stick":2812,"minecraft:oak_fence":14,"minecraft:torch":1230,"minecraft:spruce_stairs":262,"minecraft:snow_block":6,"minecraft:porkchop":64,"minecraft:netherite_shovel":5,"minecraft:diorite":1439,"minecraft:rotten_flesh":1750,"minecraft:obsidian":438,"minecraft:cod":2,"minecraft:cobblestone":19673,"minecraft:enchanting_table":1,"minecraft:leather_chestplate":2,"minecraft:lilac":9,"minecraft:magma_cream":34,"minecraft:repeater":34,"minecraft:andesite":1813,"minecraft:black_bed":97,"minecraft:golden_leggings":5,"minecraft:potato":593,"minecraft:tuff":15,"minecraft:wither_skeleton_skull":2,"minecraft:lapis_lazuli":1055,"minecraft:dirt":9323,"minecraft:polished_granite":53,"minecraft:leather_boots":4,"minecraft:glass":14,"minecraft:bone":624,"minecraft:bow":23,"minecraft:wheat_seeds":4839,"minecraft:orange_tulip":28,"minecraft:grindstone":6,"minecraft:netherite_axe":10,"minecraft:mossy_stone_bricks":1,"minecraft:fletching_table":9,"minecraft:bamboo":1147,"minecraft:powered_rail":37,"minecraft:oak_planks":67,"minecraft:cooked_porkchop":45,"minecraft:music_disc_13":4,"minecraft:poisonous_potato":2,"minecraft:sand":194,"minecraft:grass_block":2,"minecraft:diamond_block":15,"minecraft:lily_of_the_valley":24,"minecraft:mossy_cobblestone":81,"minecraft:spruce_fence_gate":15,"minecraft:sugar":6,"minecraft:diamond":305,"minecraft:spruce_boat":9,"minecraft:netherite_helmet":5,"minecraft:cracked_polished_blackstone_bricks":72,"minecraft:crossbow":6,"minecraft:bone_meal":16,"minecraft:spruce_sign":8,"minecraft:emerald":32,"minecraft:oak_sapling":27,"minecraft:netherrack":6108,"minecraft:oak_leaves":18,"minecraft:cocoa_beans":17,"minecraft:allium":40,"minecraft:azure_bluet":19,"minecraft:chicken":25,"minecraft:ladder":26,"minecraft:stone_brick_wall":5,"minecraft:cooked_rabbit":1,"minecraft:gold_block":20,"minecraft:chain":60,"minecraft:shield":10,"minecraft:oak_trapdoor":6,"minecraft:stone_stairs":87,"minecraft:iron_axe":7,"minecraft:large_fern":1,"minecraft:item_frame":10,"minecraft:blackstone":128,"minecraft:detector_rail":3,"minecraft:lectern":845,"minecraft:sugar_cane":1985,"minecraft:spruce_trapdoor":84,"minecraft:phantom_membrane":28,"minecraft:dark_oak_sapling":174,"minecraft:polished_blackstone_bricks":223,"minecraft:stone_button":27,"minecraft:iron_horse_armor":1,"minecraft:dark_oak_planks":827,"minecraft:arrow":646,"minecraft:nether_bricks":6,"minecraft:pink_tulip":80,"minecraft:saddle":7,"minecraft:netherite_boots":4,"minecraft:dark_oak_button":20,"minecraft:basalt":3,"minecraft:salmon":20,"minecraft:leather":686,"minecraft:birch_planks":7,"minecraft:ice":8,"minecraft:cobblestone_wall":1,"minecraft:gunpowder":268,"minecraft:cobblestone_stairs":22,"minecraft:cooked_mutton":34,"minecraft:red_carpet":34,"minecraft:rabbit_hide":1,"minecraft:heart_of_the_sea":1,"minecraft:spruce_wood":11,"minecraft:iron_ingot":328,"minecraft:cooked_chicken":95,"minecraft:soul_sand":63,"minecraft:book":34,"minecraft:oak_slab":1,"minecraft:warped_fungus":2,"minecraft:nether_quartz_ore":2,"minecraft:emerald_block":71,"minecraft:pumpkin":36,"minecraft:quartz":1131,"minecraft:dandelion":4,"minecraft:amethyst_shard":32,"minecraft:white_bed":6,"minecraft:gold_ore":212,"minecraft:spruce_door":41,"minecraft:spider_eye":200,"minecraft:pumpkin_seeds":150,"minecraft:campfire":23,"minecraft:iron_helmet":5,"minecraft:black_wool":792,"minecraft:dark_oak_wood":7,"minecraft:coal":4615,"minecraft:wooden_axe":2},"minecraft:broken":{"minecraft:shears":1,"minecraft:wooden_pickaxe":1,"minecraft:iron_axe":6,"minecraft:iron_pickaxe":24,"minecraft:iron_helmet":1,"minecraft:iron_shovel":13,"minecraft:stone_pickaxe":1},"minecraft:custom":{"minecraft:interact_with_crafting_table":725,"minecraft:open_barrel":80,"minecraft:leave_game":165,"minecraft:time_since_death":3760914,"minecraft:damage_blocked_by_shield":3000,"minecraft:deaths":8,"minecraft:jump":81919,"minecraft:enchant_item":51,"minecraft:interact_with_furnace":549,"minecraft:traded_with_villager":2269,"minecraft:sleep_in_bed":114,"minecraft:damage_dealt":428530,"minecraft:use_cauldron":3,"minecraft:inspect_dispenser":69,"minecraft:horse_one_cm":932758,"minecraft:interact_with_smithing_table":21,"minecraft:interact_with_anvil":83,"minecraft:inspect_hopper":62,"minecraft:sneak_time":336641,"minecraft:interact_with_stonecutter":5,"minecraft:time_since_rest":103834,"minecraft:swim_one_cm":461558,"minecraft:fly_one_cm":17922593,"minecraft:open_chest":3470,"minecraft:fall_one_cm":2160141,"minecraft:animals_bred":553,"minecraft:sprint_one_cm":16912542,"minecraft:drop":1695,"minecraft:talked_to_villager":1701,"minecraft:walk_on_water_one_cm":589507,"minecraft:play_one_minute":8244018,"minecraft:interact_with_loom":9,"minecraft:open_enderchest":162,"minecraft:player_kills":15,"minecraft:crouch_one_cm":899348,"minecraft:mob_kills":3159,"minecraft:fill_cauldron":6,"minecraft:climb_one_cm":295806,"minecraft:walk_one_cm":18892826,"minecraft:raid_win":2,"minecraft:strider_one_cm":30467,"minecraft:walk_under_water_one_cm":1355304,"minecraft:boat_one_cm":121226,"minecraft:raid_trigger":2,"minecraft:interact_with_grindstone":21,"minecraft:damage_taken":45719,"minecraft:trigger_trapped_chest":49,"minecraft:minecart_one_cm":758048},"minecraft:killed_by":{"minecraft:creeper":3,"minecraft:player":2},"minecraft:used":{"minecraft:dispenser":2,"minecraft:spruce_slab":2104,"minecraft:ladder":111,"minecraft:poppy":1,"minecraft:chest":179,"minecraft:stone":4321,"minecraft:rotten_flesh":3,"minecraft:soul_sand":1,"minecraft:snowball":294,"minecraft:stripped_spruce_log":1,"minecraft:spruce_boat":10,"minecraft:lava_bucket":2,"minecraft:netherite_shovel":8681,"minecraft:red_wool":1,"minecraft:polished_andesite_stairs":26,"minecraft:copper_ore":2,"minecraft:dark_oak_leaves":4,"minecraft:dark_oak_slab":570,"minecraft:dark_oak_button":22,"minecraft:snow":275,"minecraft:bow":132,"minecraft:furnace":23,"minecraft:egg":90,"minecraft:potato":249,"minecraft:diorite":55,"minecraft:spruce_door":45,"minecraft:warped_fungus_on_a_stick":25,"minecraft:powered_rail":275,"minecraft:blackstone":74,"minecraft:wooden_pickaxe":59,"minecraft:composter":15,"minecraft:dark_oak_trapdoor":398,"minecraft:pumpkin_seeds":19,"minecraft:stone_button":43,"minecraft:lectern":862,"minecraft:polished_granite":71,"minecraft:smithing_table":3,"minecraft:dark_oak_fence":83,"minecraft:ice":4,"minecraft:compass":3,"minecraft:oak_trapdoor":13,"minecraft:iron_bars":9,"minecraft:enchanting_table":2,"minecraft:stone_sword":7,"minecraft:carved_pumpkin":11,"minecraft:armor_stand":10,"minecraft:cooked_salmon":6,"minecraft:torch":1814,"minecraft:netherrack":964,"minecraft:anvil":6,"minecraft:warped_wart_block":5,"minecraft:nether_quartz_ore":2,"minecraft:stone_stairs":84,"minecraft:oak_fence_gate":2,"minecraft:polished_diorite":51,"minecraft:chipped_anvil":2,"minecraft:light_weighted_pressure_plate":9,"minecraft:iron_axe":1293,"minecraft:spruce_button":1,"minecraft:barrel":57,"minecraft:bamboo":85,"minecraft:glowstone":9,"minecraft:trapped_chest":1,"minecraft:wheat_seeds":1825,"minecraft:water_bucket":562,"minecraft:cauldron":6,"minecraft:fletching_table":17,"minecraft:spruce_fence_gate":16,"minecraft:polished_blackstone_bricks":158,"minecraft:diamond_block":15,"minecraft:mossy_cobblestone":2,"minecraft:rail":156,"minecraft:comparator":18,"minecraft:red_bed":1,"minecraft:crafting_table":70,"minecraft:white_bed":25,"minecraft:campfire":43,"minecraft:spruce_log":3019,"minecraft:oak_log":1,"minecraft:diamond_pickaxe":56,"minecraft:iron_pickaxe":6318,"minecraft:suspicious_stew":1,"minecraft:spruce_pressure_plate":18,"minecraft:spruce_trapdoor":140,"minecraft:spruce_sapling":1223,"minecraft:cobblestone":5743,"minecraft:purple_bed":5,"minecraft:cooked_porkchop":49,"minecraft:glass_pane":385,"minecraft:blue_terracotta":1,"minecraft:iron_shovel":3258,"minecraft:oak_sign":6,"minecraft:shield":69,"minecraft:iron_sword":161,"minecraft:spruce_leaves":93,"minecraft:nether_bricks":5,"minecraft:carrot":239,"minecraft:obsidian":27,"minecraft:glass":6,"minecraft:bricks":20,"minecraft:coal_ore":13,"minecraft:spruce_wood":53,"minecraft:lantern":301,"minecraft:warped_nylium":1,"minecraft:dark_oak_wood":10,"minecraft:stone_bricks":41,"minecraft:item_frame":26,"minecraft:repeater":60,"minecraft:red_carpet":236,"minecraft:magma_block":2,"minecraft:hay_block":18,"minecraft:dark_oak_sapling":158,"minecraft:dark_oak_stairs":778,"minecraft:stone_pickaxe":237,"minecraft:ender_pearl":6,"minecraft:redstone_block":12,"minecraft:sugar_cane":206,"minecraft:blue_bed":4,"minecraft:white_wool":1,"minecraft:loom":2,"minecraft:crossbow":164,"minecraft:stone_brick_wall":162,"minecraft:black_bed":186,"minecraft:shears":58,"minecraft:sticky_piston":4,"minecraft:redstone_torch":27,"minecraft:lever":84,"minecraft:dark_oak_log":36,"minecraft:heavy_weighted_pressure_plate":2,"minecraft:bread":51,"minecraft:iron_door":16,"minecraft:gravel":68,"minecraft:grindstone":6,"minecraft:cooked_rabbit":1,"minecraft:andesite":105,"minecraft:chain":109,"minecraft:chest_minecart":4,"minecraft:smooth_stone_slab":23,"minecraft:tropical_fish_bucket":3,"minecraft:bone_meal":791,"minecraft:netherite_sword":4615,"minecraft:oak_fence":8,"minecraft:white_tulip":1,"minecraft:flint_and_steel":5,"minecraft:redstone_ore":13,"minecraft:redstone":572,"minecraft:spruce_planks":4408,"minecraft:ender_chest":22,"minecraft:wooden_shovel":6,"minecraft:cooked_chicken":261,"minecraft:oak_door":4,"minecraft:dirt":9541,"minecraft:white_carpet":26,"minecraft:hopper":107,"minecraft:spruce_stairs":464,"minecraft:spruce_fence":927,"minecraft:granite":152,"minecraft:iron_hoe":521,"minecraft:dark_oak_planks":3639,"minecraft:wooden_axe":1,"minecraft:bookshelf":103,"minecraft:golden_carrot":34,"minecraft:dark_oak_pressure_plate":14,"minecraft:white_stained_glass_pane":1,"minecraft:minecart":58,"minecraft:netherite_pickaxe":51214,"minecraft:cooked_beef":679,"minecraft:powder_snow_bucket":2,"minecraft:pumpkin":8,"minecraft:cooked_mutton":46,"minecraft:iron_ore":1,"minecraft:cobblestone_stairs":54,"minecraft:lodestone":2,"minecraft:snow_block":40,"minecraft:polished_andesite":223,"minecraft:red_nether_bricks":2,"minecraft:blue_wool":1,"minecraft:spruce_sign":8,"minecraft:stonecutter":2,"minecraft:cobblestone_slab":91,"minecraft:painting":96,"minecraft:dark_oak_door":34,"minecraft:piston":2,"minecraft:flower_pot":5,"minecraft:cracked_polished_blackstone_bricks":59,"minecraft:map":8,"minecraft:netherite_axe":20218,"minecraft:detector_rail":9,"minecraft:stone_slab":56,"minecraft:stone_axe":43,"minecraft:white_banner":11,"minecraft:bucket":572,"minecraft:smooth_stone":15},"minecraft:dropped":{"minecraft:iron_sword":3,"minecraft:lapis_lazuli":42,"minecraft:cooked_beef":130,"minecraft:diamond":33,"minecraft:crossbow":2,"minecraft:dark_oak_slab":3,"minecraft:warped_roots":13,"minecraft:black_bed":89,"minecraft:dark_oak_button":1,"minecraft:rail":4,"minecraft:red_mushroom":1,"minecraft:emerald":1,"minecraft:dirt":698,"minecraft:stone_button":2,"minecraft:dark_oak_trapdoor":1,"minecraft:netherite_boots":1,"minecraft:gold_nugget":64,"minecraft:bone_meal":6,"minecraft:phantom_membrane":3,"minecraft:sand":54,"minecraft:sugar":2,"minecraft:iron_pickaxe":1,"minecraft:dark_oak_planks":151,"minecraft:white_wool":1,"minecraft:bone":56,"minecraft:dark_oak_door":1,"minecraft:stone_axe":3,"minecraft:compass":1,"minecraft:sugar_cane":4,"minecraft:lever":9,"minecraft:iron_nugget":87,"minecraft:cooked_chicken":65,"minecraft:golden_chestplate":1,"minecraft:netherite_sword":3,"minecraft:wheat":3,"minecraft:rotten_flesh":739,"minecraft:oak_planks":6,"minecraft:glowstone_dust":2,"minecraft:white_bed":3,"minecraft:heavy_weighted_pressure_plate":1,"minecraft:coal_ore":6,"minecraft:leather_boots":1,"minecraft:ladder":5,"minecraft:leather_leggings":4,"minecraft:spruce_slab":17,"minecraft:glass":14,"minecraft:campfire":1,"minecraft:warped_wart_block":3,"minecraft:egg":7,"minecraft:enchanted_book":2,"minecraft:golden_boots":3,"minecraft:iron_ingot":19,"minecraft:netherite_pickaxe":2,"minecraft:wheat_seeds":2195,"minecraft:netherite_helmet":1,"minecraft:netherite_chestplate":2,"minecraft:iron_helmet":1,"minecraft:feather":5,"minecraft:cobblestone":1245,"minecraft:book":6,"minecraft:granite":344,"minecraft:spruce_button":1,"minecraft:command_block":2,"minecraft:spruce_door":1,"minecraft:coal":44,"minecraft:dark_oak_leaves":7,"minecraft:gray_wool":2,"minecraft:golden_carrot":10,"minecraft:ink_sac":2,"minecraft:wooden_axe":2,"minecraft:cooked_salmon":5,"minecraft:string":34,"minecraft:spruce_sapling":17,"minecraft:furnace":1,"minecraft:redstone_ore":2,"minecraft:stone_sword":6,"minecraft:chicken":2,"minecraft:spruce_fence":18,"minecraft:shears":1,"minecraft:pumpkin_seeds":28,"minecraft:potato":2,"minecraft:hay_block":2,"minecraft:stone":155,"minecraft:spruce_trapdoor":25,"minecraft:spruce_planks":81,"minecraft:wooden_shovel":2,"minecraft:spider_eye":30,"minecraft:stone_bricks":50,"minecraft:bamboo":30,"minecraft:bow":12,"minecraft:magma_block":28,"minecraft:black_wool":3,"minecraft:crimson_nylium":2,"minecraft:warped_stem":10,"minecraft:birch_planks":1,"minecraft:dark_oak_stairs":5,"minecraft:leather":4,"minecraft:cod":2,"minecraft:flint":135,"minecraft:spruce_leaves":94,"minecraft:cracked_polished_blackstone_bricks":12,"minecraft:ice":4,"minecraft:cornflower":1,"minecraft:cooked_cod":5,"minecraft:snowball":70,"minecraft:gravel":135,"minecraft:blackstone":4,"minecraft:carrot":3,"minecraft:rabbit_hide":1,"minecraft:poppy":7,"minecraft:gunpowder":25,"minecraft:stone_brick_wall":17,"minecraft:beetroot_seeds":1,"minecraft:basalt":2,"minecraft:arrow":70,"minecraft:quartz":110,"minecraft:netherrack":802,"minecraft:oak_slab":1,"minecraft:water_bucket":4,"minecraft:bread":318,"minecraft:golden_helmet":2,"minecraft:diamond_leggings":1,"minecraft:poisonous_potato":1,"minecraft:netherite_axe":5,"minecraft:spruce_stairs":1,"minecraft:stick":2245,"minecraft:diorite":301,"minecraft:torch":18,"minecraft:iron_leggings":2,"minecraft:dandelion":1,"minecraft:redstone":93,"minecraft:warped_nylium":1,"minecraft:ender_chest":5,"minecraft:totem_of_undying":1,"minecraft:netherite_leggings":1,"minecraft:copper_ore":5,"minecraft:filled_map":1,"minecraft:snow":1,"minecraft:shield":2,"minecraft:diamond_chestplate":1,"minecraft:andesite":390,"minecraft:golden_leggings":1,"minecraft:spruce_log":128,"minecraft:stone_pickaxe":1}},"DataVersion":2683}